{
  "annotations": {
    "list": [
      {
        "builtIn": 1,
        "datasource": {
          "type": "grafana",
          "uid": "-- Grafana --"
        },
        "enable": true,
        "hide": true,
        "iconColor": "rgba(0, 211, 255, 1)",
        "name": "Annotations & Alerts",
        "type": "dashboard"
      }
    ]
  },
  "editable": true,
  "fiscalYearStartMonth": 0,
  "graphTooltip": 1,
  "id": null,
  "links": [],
  "panels": [
    {
      "datasource": {
        "type": "prometheus",
        "uid": "$datasource"
      },
      "fieldConfig": {
        "defaults": {
          "color": {
            "mode": "thresholds"
          },
          "mappings": [
            {
              "options": {
                "0": {
                  "color": "red",
                  "index": 0,
                  "text": "Disconnected"
                },
                "1": {
                  "color": "green",
                  "index": 1,
                  "text": "Connected"
                }
              },
              "type": "value"
            }
          ],
          "thresholds": {
            "mode": "absolute",
            "steps": [
              {
                "color": "red",
                "value": null
              },
              {
                "color": "green",
                "value": 1
              }
            ]
          }
        },
        "overrides": []
      },
      "gridPos": {
        "h": 4,
        "w": 6,
        "x": 0,
        "y": 0
      },
      "id": 1,
      "options": {
        "colorMode": "value",
        "graphMode": "none",
        "justifyMode": "auto",
        "orientation": "auto",
        "reduceOptions": {
          "calcs": [
            "lastNotNull"
          ],
          "fields": "",
          "values": false
        },
        "textMode": "auto"
      },
      "targets": [
        {
          "datasource": {
            "type": "prometheus",
            "uid": "$datasource"
          },
          "editorMode": "code",
          "expr": "gardena_exporter_connected",
          "instant": true,
          "legendFormat": "",
          "range": false,
          "refId": "A"
        }
      ],
      "title": "Exporter Connection",
      "type": "stat"
    },
    {
      "datasource": {
        "type": "prometheus",
        "uid": "$datasource"
      },
      "fieldConfig": {
        "defaults": {
          "color": {
            "mode": "palette-classic"
          },
          "decimals": 0,
          "min": 0
        },
        "overrides": []
      },
      "gridPos": {
        "h": 4,
        "w": 6,
        "x": 6,
        "y": 0
      },
      "id": 2,
      "options": {
        "colorMode": "background",
        "graphMode": "none",
        "justifyMode": "auto",
        "orientation": "auto",
        "reduceOptions": {
          "calcs": [
            "lastNotNull"
          ],
          "fields": "",
          "values": false
        },
        "textMode": "value"
      },
      "targets": [
        {
          "datasource": {
            "type": "prometheus",
            "uid": "$datasource"
          },
          "editorMode": "code",
          "expr": "sum(gardena_valve_open{location=~\"$location\"})",
          "instant": true,
          "legendFormat": "",
          "range": false,
          "refId": "A"
        }
      ],
      "title": "Active Valves",
      "type": "stat"
    },
    {
      "datasource": {
        "type": "prometheus",
        "uid": "$datasource"
      },
      "fieldConfig": {
        "defaults": {
          "color": {
            "mode": "thresholds"
          },
          "max": 100,
          "min": 0,
          "thresholds": {
            "mode": "absolute",
            "steps": [
              {
                "color": "red",
                "value": null
              },
              {
                "color": "orange",
                "value": 30
              },
              {
                "color": "green",
                "value": 50
              }
            ]
          },
          "unit": "percent"
        },
        "overrides": []
      },
      "gridPos": {
        "h": 4,
        "w": 6,
        "x": 12,
        "y": 0
      },
      "id": 3,
      "options": {
        "colorMode": "background",
        "graphMode": "none",
        "justifyMode": "auto",
        "orientation": "auto",
        "reduceOptions": {
          "calcs": [
            "mean"
          ],
          "fields": "",
          "values": false
        },
        "textMode": "value_and_name"
      },
      "targets": [
        {
          "datasource": {
            "type": "prometheus",
            "uid": "$datasource"
          },
          "editorMode": "code",
          "expr": "avg(gardena_sensor_soil_humidity_percent{location=~\"$location\"})",
          "instant": true,
          "legendFormat": "",
          "range": false,
          "refId": "A"
        }
      ],
      "title": "Average Soil Humidity",
      "type": "stat"
    },
    {
      "datasource": {
        "type": "prometheus",
        "uid": "$datasource"
      },
      "fieldConfig": {
        "defaults": {
          "color": {
            "mode": "thresholds"
          },
          "max": 100,
          "min": 0,
          "thresholds": {
            "mode": "absolute",
            "steps": [
              {
                "color": "red",
                "value": null
              },
              {
                "color": "orange",
                "value": 25
              },
              {
                "color": "green",
                "value": 50
              }
            ]
          },
          "unit": "percent"
        },
        "overrides": []
      },
      "gridPos": {
        "h": 4,
        "w": 6,
        "x": 18,
        "y": 0
      },
      "id": 4,
      "options": {
        "colorMode": "background",
        "graphMode": "none",
        "justifyMode": "auto",
        "orientation": "auto",
        "reduceOptions": {
          "calcs": [
            "min"
          ],
          "fields": "",
          "values": false
        },
        "textMode": "value_and_name"
      },
      "targets": [
        {
          "datasource": {
            "type": "prometheus",
            "uid": "$datasource"
          },
          "editorMode": "code",
          "expr": "min(gardena_device_battery_level_percent{location=~\"$location\"})",
          "instant": true,
          "legendFormat": "",
          "range": false,
          "refId": "A"
        }
      ],
      "title": "Lowest Battery",
      "type": "stat"
    },
    {
      "datasource": {
        "type": "prometheus",
        "uid": "$datasource"
      },
      "fieldConfig": {
        "defaults": {
          "color": {
            "mode": "thresholds"
          },
          "custom": {
            "axisCenteredZero": false,
            "axisColorMode": "text",
            "axisLabel": "",
            "axisPlacement": "auto",
            "barAlignment": 0,
            "drawStyle": "bars",
            "fillOpacity": 70,
            "gradientMode": "none",
            "hideFrom": {
              "legend": false,
              "tooltip": false,
              "viz": false
            },
            "lineInterpolation": "linear",
            "lineWidth": 1,
            "pointSize": 5,
            "scaleDistribution": {
              "type": "linear"
            },
            "showPoints": "never",
            "spanNulls": false,
            "stacking": {
              "group": "A",
              "mode": "none"
            },
            "thresholdsStyle": {
              "mode": "off"
            }
          },
          "max": 100,
          "min": 0,
          "unit": "percent"
        },
        "overrides": []
      },
      "gridPos": {
        "h": 8,
        "w": 12,
        "x": 0,
        "y": 4
      },
      "id": 5,
      "options": {
        "legend": {
          "calcs": [],
          "displayMode": "list",
          "placement": "bottom",
          "showLegend": true
        },
        "tooltip": {
          "mode": "single",
          "sort": "none"
        }
      },
      "targets": [
        {
          "datasource": {
            "type": "prometheus",
            "uid": "$datasource"
          },
          "editorMode": "code",
          "expr": "gardena_sensor_soil_humidity_percent{location=~\"$location\"}",
          "instant": false,
          "legendFormat": "{{device_name}}",
          "range": true,
          "refId": "A"
        }
      ],
      "title": "Soil Humidity by Zone",
      "type": "timeseries"
    },
    {
      "datasource": {
        "type": "prometheus",
        "uid": "$datasource"
      },
      "fieldConfig": {
        "defaults": {
          "color": {
            "mode": "palette-classic"
          },
          "custom": {
            "axisCenteredZero": false,
            "axisColorMode": "text",
            "axisLabel": "",
            "axisPlacement": "auto",
            "barAlignment": 0,
            "drawStyle": "line",
            "fillOpacity": 16,
            "gradientMode": "none",
            "hideFrom": {
              "legend": false,
              "tooltip": false,
              "viz": false
            },
            "lineInterpolation": "linear",
            "lineWidth": 2,
            "pointSize": 5,
            "scaleDistribution": {
              "type": "linear"
            },
            "showPoints": "auto",
            "spanNulls": false,
            "stacking": {
              "group": "A",
              "mode": "none"
            },
            "thresholdsStyle": {
              "mode": "off"
            }
          },
          "unit": "celsius"
        },
        "overrides": []
      },
      "gridPos": {
        "h": 8,
        "w": 12,
        "x": 12,
        "y": 4
      },
      "id": 6,
      "options": {
        "legend": {
          "calcs": [],
          "displayMode": "list",
          "placement": "bottom",
          "showLegend": true
        },
        "tooltip": {
          "mode": "multi",
          "sort": "none"
        }
      },
      "targets": [
        {
          "datasource": {
            "type": "prometheus",
            "uid": "$datasource"
          },
          "editorMode": "code",
          "expr": "gardena_sensor_soil_temperature_celsius{location=~\"$location\"}",
          "instant": false,
          "legendFormat": "{{device_name}}",
          "range": true,
          "refId": "A"
        }
      ],
      "title": "Soil Temperature by Zone",
      "type": "timeseries"
    },
    {
      "datasource": {
        "type": "prometheus",
        "uid": "$datasource"
      },
      "fieldConfig": {
        "defaults": {
          "color": {
            "mode": "palette-classic"
          },
          "custom": {
            "axisCenteredZero": false,
            "axisColorMode": "text",
            "axisLabel": "",
            "axisPlacement": "auto",
            "barAlignment": 0,
            "drawStyle": "line",
            "fillOpacity": 10,
            "gradientMode": "none",
            "hideFrom": {
              "legend": false,
              "tooltip": false,
              "viz": false
            },
            "lineInterpolation": "linear",
            "lineWidth": 2,
            "pointSize": 4,
            "scaleDistribution": {
              "type": "linear"
            },
            "showPoints": "auto",
            "spanNulls": false,
            "stacking": {
              "group": "A",
              "mode": "none"
            },
            "thresholdsStyle": {
              "mode": "off"
            }
          },
          "unit": "celsius"
        },
        "overrides": []
      },
      "gridPos": {
        "h": 8,
        "w": 12,
        "x": 0,
        "y": 12
      },
      "id": 7,
      "options": {
        "legend": {
          "calcs": [],
          "displayMode": "list",
          "placement": "bottom",
          "showLegend": true
        },
        "tooltip": {
          "mode": "multi",
          "sort": "none"
        }
      },
      "targets": [
        {
          "datasource": {
            "type": "prometheus",
            "uid": "$datasource"
          },
          "editorMode": "code",
          "expr": "gardena_sensor_ambient_temperature_celsius{location=~\"$location\"}",
          "instant": false,
          "legendFormat": "{{device_name}}",
          "range": true,
          "refId": "A"
        }
      ],
      "title": "Ambient Temperature",
      "type": "timeseries"
    },
    {
      "datasource": {
        "type": "prometheus",
        "uid": "$datasource"
      },
      "fieldConfig": {
        "defaults": {
          "color": {
            "mode": "palette-classic"
          },
          "custom": {
            "axisCenteredZero": false,
            "axisColorMode": "text",
            "axisLabel": "",
            "axisPlacement": "auto",
            "barAlignment": 0,
            "drawStyle": "line",
            "fillOpacity": 10,
            "gradientMode": "none",
            "hideFrom": {
              "legend": false,
              "tooltip": false,
              "viz": false
            },
            "lineInterpolation": "linear",
            "lineWidth": 2,
            "pointSize": 4,
            "scaleDistribution": {
              "type": "linear"
            },
            "showPoints": "auto",
            "spanNulls": false,
            "stacking": {
              "group": "A",
              "mode": "none"
            },
            "thresholdsStyle": {
              "mode": "off"
            }
          },
          "unit": "lux"
        },
        "overrides": []
      },
      "gridPos": {
        "h": 8,
        "w": 12,
        "x": 12,
        "y": 12
      },
      "id": 8,
      "options": {
        "legend": {
          "calcs": [],
          "displayMode": "list",
          "placement": "bottom",
          "showLegend": true
        },
        "tooltip": {
          "mode": "multi",
          "sort": "none"
        }
      },
      "targets": [
        {
          "datasource": {
            "type": "prometheus",
            "uid": "$datasource"
          },
          "editorMode": "code",
          "expr": "gardena_sensor_light_intensity_lux{location=~\"$location\"}",
          "instant": false,
          "legendFormat": "{{device_name}}",
          "range": true,
          "refId": "A"
        }
      ],
      "title": "Light Intensity",
      "type": "timeseries"
    },
    {
      "datasource": {
        "type": "prometheus",
        "uid": "$datasource"
      },
      "fieldConfig": {
        "defaults": {
          "color": {
            "mode": "thresholds"
          },
          "custom": {
            "axisCenteredZero": false,
            "axisColorMode": "text",
            "axisLabel": "",
            "axisPlacement": "auto",
            "barAlignment": 0,
            "drawStyle": "bars",
            "fillOpacity": 80,
            "gradientMode": "none",
            "hideFrom": {
              "legend": false,
              "tooltip": false,
              "viz": false
            },
            "lineInterpolation": "linear",
            "lineWidth": 1,
            "pointSize": 5,
            "scaleDistribution": {
              "type": "linear"
            },
            "showPoints": "never",
            "spanNulls": false,
            "stacking": {
              "group": "A",
              "mode": "none"
            },
            "thresholdsStyle": {
              "mode": "off"
            }
          },
          "max": 100,
          "min": 0,
          "thresholds": {
            "mode": "absolute",
            "steps": [
              {
                "color": "red",
                "value": null
              },
              {
                "color": "orange",
                "value": 20
              },
              {
                "color": "green",
                "value": 50
              }
            ]
          },
          "unit": "percent"
        },
        "overrides": []
      },
      "gridPos": {
        "h": 8,
        "w": 12,
        "x": 0,
        "y": 20
      },
      "id": 9,
      "options": {
        "legend": {
          "calcs": [],
          "displayMode": "list",
          "placement": "bottom",
          "showLegend": true
        },
        "tooltip": {
          "mode": "single",
          "sort": "none"
        }
      },
      "targets": [
        {
          "datasource": {
            "type": "prometheus",
            "uid": "$datasource"
          },
          "editorMode": "code",
          "expr": "gardena_device_battery_level_percent{location=~\"$location\"}",
          "instant": false,
          "legendFormat": "{{device_name}}",
          "range": true,
          "refId": "A"
        }
      ],
      "title": "Battery Levels",
      "type": "timeseries"
    },
    {
      "datasource": {
        "type": "prometheus",
        "uid": "$datasource"
      },
      "fieldConfig": {
        "defaults": {
          "color": {
            "mode": "palette-classic"
          },
          "custom": {
            "axisCenteredZero": false,
            "axisColorMode": "text",
            "axisLabel": "",
            "axisPlacement": "auto",
            "barAlignment": 0,
            "drawStyle": "bars",
            "fillOpacity": 80,
            "gradientMode": "none",
            "hideFrom": {
              "legend": false,
              "tooltip": false,
              "viz": false
            },
            "lineInterpolation": "linear",
            "lineWidth": 1,
            "pointSize": 5,
            "scaleDistribution": {
              "type": "linear"
            },
            "showPoints": "never",
            "spanNulls": false,
            "stacking": {
              "group": "A",
              "mode": "none"
            },
            "thresholdsStyle": {
              "mode": "off"
            }
          },
          "max": 100,
          "min": 0,
          "unit": "percent"
        },
        "overrides": []
      },
      "gridPos": {
        "h": 8,
        "w": 12,
        "x": 12,
        "y": 20
      },
      "id": 10,
      "options": {
        "legend": {
          "calcs": [],
          "displayMode": "list",
          "placement": "bottom",
          "showLegend": true
        },
        "tooltip": {
          "mode": "single",
          "sort": "none"
        }
      },
      "targets": [
        {
          "datasource": {
            "type": "prometheus",
            "uid": "$datasource"
          },
          "editorMode": "code",
          "expr": "gardena_device_rf_link_level_percent{location=~\"$location\"}",
          "instant": false,
          "legendFormat": "{{device_name}}",
          "range": true,
          "refId": "A"
        }
      ],
      "title": "RF Link Levels",
      "type": "timeseries"
    },
    {
      "datasource": {
        "type": "prometheus",
        "uid": "$datasource"
      },
      "fieldConfig": {
        "defaults": {
          "color": {
            "mode": "thresholds"
          },
          "custom": {
            "align": "auto",
            "cellOptions": {
              "type": "auto"
            },
            "inspect": false
          },
          "mappings": [],
          "thresholds": {
            "mode": "absolute",
            "steps": [
              {
                "color": "green",
                "value": null
              }
            ]
          }
        },
        "overrides": []
      },
      "gridPos": {
        "h": 8,
        "w": 24,
        "x": 0,
        "y": 28
      },
      "id": 11,
      "options": {
        "cellHeight": "sm",
        "footer": {
          "countRows": false,
          "fields": "",
          "reducer": [
            "sum"
          ],
          "show": false
        },
        "showHeader": true
      },
      "targets": [
        {
          "datasource": {
            "type": "prometheus",
            "uid": "$datasource"
          },
          "editorMode": "code",
          "expr": "gardena_valve_info{location=~\"$location\"}",
          "format": "table",
          "instant": true,
          "range": false,
          "refId": "A"
        }
      ],
      "title": "Valve Status Table",
      "type": "table"
    },
    {
      "datasource": {
        "type": "prometheus",
        "uid": "$datasource"
      },
      "fieldConfig": {
        "defaults": {
          "color": {
            "mode": "palette-classic"
          },
          "decimals": 1,
          "min": 0,
          "unit": "liter"
        },
        "overrides": []
      },
      "gridPos": {
        "h": 4,
        "w": 6,
        "x": 0,
        "y": 36
      },
      "id": 12,
      "options": {
        "colorMode": "background",
        "graphMode": "none",
        "justifyMode": "auto",
        "orientation": "auto",
        "reduceOptions": {
          "calcs": [
            "lastNotNull"
          ],
          "fields": "",
          "values": false
        },
        "textMode": "value_and_name"
      },
      "targets": [
        {
          "datasource": {
            "type": "prometheus",
            "uid": "$datasource"
          },
          "editorMode": "code",
          "expr": "increase(gardena_estimated_water_liters_total{location=~\"$location\"}[$__range])",
          "instant": true,
          "legendFormat": "",
          "range": false,
          "refId": "A"
        }
      ],
      "title": "Estimated Water (Selected Range)",
      "type": "stat"
    },
    {
      "datasource": {
        "type": "prometheus",
        "uid": "$datasource"
      },
      "fieldConfig": {
        "defaults": {
          "color": {
            "mode": "palette-classic"
          },
          "decimals": 2,
          "min": 0
        },
        "overrides": []
      },
      "gridPos": {
        "h": 4,
        "w": 6,
        "x": 6,
        "y": 36
      },
      "id": 13,
      "options": {
        "colorMode": "background",
        "graphMode": "none",
        "justifyMode": "auto",
        "orientation": "auto",
        "reduceOptions": {
          "calcs": [
            "lastNotNull"
          ],
          "fields": "",
          "values": false
        },
        "textMode": "value_and_name"
      },
      "targets": [
        {
          "datasource": {
            "type": "prometheus",
            "uid": "$datasource"
          },
          "editorMode": "code",
          "expr": "gardena_estimated_current_water_flow_liters_per_minute{location=~\"$location\"}",
          "instant": true,
          "legendFormat": "",
          "range": false,
          "refId": "A"
        }
      ],
      "title": "Modeled Current Flow (L/min)",
      "type": "stat"
    },
    {
      "datasource": {
        "type": "prometheus",
        "uid": "$datasource"
      },
      "fieldConfig": {
        "defaults": {
          "color": {
            "mode": "palette-classic"
          },
          "custom": {
            "axisCenteredZero": false,
            "axisColorMode": "text",
            "axisLabel": "",
            "axisPlacement": "auto",
            "barAlignment": 0,
            "drawStyle": "line",
            "fillOpacity": 12,
            "gradientMode": "none",
            "hideFrom": {
              "legend": false,
              "tooltip": false,
              "viz": false
            },
            "lineInterpolation": "linear",
            "lineWidth": 2,
            "pointSize": 4,
            "scaleDistribution": {
              "type": "linear"
            },
            "showPoints": "auto",
            "spanNulls": false,
            "stacking": {
              "group": "A",
              "mode": "none"
            },
            "thresholdsStyle": {
              "mode": "off"
            }
          },
          "min": 0,
          "unit": "liter"
        },
        "overrides": []
      },
      "gridPos": {
        "h": 8,
        "w": 12,
        "x": 12,
        "y": 36
      },
      "id": 14,
      "options": {
        "legend": {
          "calcs": [],
          "displayMode": "list",
          "placement": "bottom",
          "showLegend": true
        },
        "tooltip": {
          "mode": "multi",
          "sort": "none"
        }
      },
      "targets": [
        {
          "datasource": {
            "type": "prometheus",
            "uid": "$datasource"
          },
          "editorMode": "code",
          "expr": "gardena_valve_estimated_water_liters_total{location=~\"$location\"}",
          "instant": false,
          "legendFormat": "{{valve_name}}",
          "range": true,
          "refId": "A"
        }
      ],
      "title": "Estimated Water by Zone",
      "type": "timeseries"
    }
  ],
  "refresh": "30s",
  "schemaVersion": 39,
  "style": "dark",
  "tags": [
    "gardena",
    "watering",
    "prometheus"
  ],
  "templating": {
    "list": [
      {
        "current": {
          "selected": true,
          "text": "default",
          "value": "default"
        },
        "hide": 0,
        "includeAll": false,
        "label": "Datasource",
        "multi": false,
        "name": "datasource",
        "options": [],
        "query": "prometheus",
        "refresh": 1,
        "regex": "",
        "skipUrlSync": false,
        "type": "datasource"
      },
      {
        "current": {
          "selected": true,
          "text": ".*",
          "value": ".*"
        },
        "datasource": {
          "type": "prometheus",
          "uid": "$datasource"
        },
        "definition": "label_values(gardena_exporter_info, location)",
        "hide": 0,
        "includeAll": true,
        "label": "Location",
        "multi": false,
        "name": "location",
        "options": [],
        "query": {
          "qryType": 1,
          "query": "label_values(gardena_exporter_info, location)",
          "refId": "PrometheusVariableQueryEditor-VariableQuery"
        },
        "refresh": 1,
        "regex": "",
        "skipUrlSync": false,
        "sort": 1,
        "type": "query"
      }
    ]
  },
  "time": {
    "from": "now-24h",
    "to": "now"
  },
  "timepicker": {},
  "timezone": "",
  "title": "Gardena Smart System",
  "uid": "gardena-smart-system",
  "version": 2,
  "weekStart": ""
}
